{
  "incidentRec":[ 
  		{"irid": "10044", "type": "Road Works", "state": "In Progress", "zone": "zone2", "roadname": "PIE", "lanes":"3 2"},
    	{"irid": "53434", "type": "Mobile Road Works", "state": "In Progress", "zone": "zone2", "roadname": "KPE", "lanes":"3 2"},
    	{"irid": "85344", "type": "Unattended Vehicle", "state": "Notified", "zone": "zone1", "roadname": "TPE", "lanes":"2"},
    	{"irid": "56834", "type": "Obstacle", "state": "Notified", "zone": "zone3", "roadname": "tun", "lanes":"1 4 2"},
    	{"irid": "34895", "type": "Accident", "state": "confirmed", "zone": "zone1", "roadname": "TPE", "lanes":"1 2 3"},
    	{"irid": "87470", "type": "Accident", "state": "over", "zone": "zone1", "roadname": "kpe", "lanes":"4 2"},
    	{"irid": "33334", "type": "Break Down", "state": "over", "zone": "zone4", "roadname": "tun", "lanes":"2 2"},
    	{"irid": "89346", "type": "Obstacle", "state": "Notified", "zone": "zone3", "roadname": "tun", "lanes":"1 4 2"},
    	{"irid": "45344", "type": "Road Works", "state": "over", "zone": "zone5", "roadname": "TPE", "lanes":"3 2"},
    	{"irid": "35224", "type": "Miscellaneous", "state": "over", "zone": "zone4", "roadname": "KPE", "lanes":"1 2"}
  	]
}

