{
  "incidentRec":[ 
  		{"irid": "0106344", "type": "Accident", "state": "confirmed", "zone": "zone1", "roadname": "TPE", "lanes":"1 2 3"},
    	{"irid": "212344", "type": "Obstacle", "state": "Notified", "zone": "zone3", "roadname": "tun", "lanes":"1 4 2"},
    	{"irid": "1005344", "type": "Road Works", "state": "In Progress", "zone": "zone2", "roadname": "PIE", "lanes":"3 2"},
    	{"irid": "122344", "type": "Accident", "state": "over", "zone": "zone1", "roadname": "kpe", "lanes":"4 2"},
    	{"irid": "33334", "type": "Break Down", "state": "over", "zone": "zone4", "roadname": "tun", "lanes":"2 2"},
    	{"irid": "212344", "type": "Obstacle", "state": "Notified", "zone": "zone3", "roadname": "tun", "lanes":"1 4 2"},
    	{"irid": "85344", "type": "Road Works", "state": "over", "zone": "zone5", "roadname": "TPE", "lanes":"3 2"}
  	]
}

